MANIFEST.in
README.md
setup.py
yanyulong/__init__.py
yanyulong.egg-info/PKG-INFO
yanyulong.egg-info/SOURCES.txt
yanyulong.egg-info/dependency_links.txt
yanyulong.egg-info/requires.txt
yanyulong.egg-info/top_level.txt