Metadata-Version: 2.1
Name: yanyulong
Version: 1.0.12
Summary: test demo for yanyulong
Author: yulong
Author-email: 
Keywords: python,test,yanyulong,windows,mac,linux
Classifier: Development Status :: 1 - Planning
Classifier: Intended Audience :: Developers
Classifier: Programming Language :: Python :: 3
Classifier: Operating System :: Unix
Classifier: Operating System :: MacOS :: MacOS X
Classifier: Operating System :: Microsoft :: Windows
